{
  "project_info": {
    "project_number": "404388630261",
    "firebase_url": "https://capstone-bangkit-b0a59-default-rtdb.asia-southeast1.firebasedatabase.app",
    "project_id": "capstone-bangkit-b0a59",
    "storage_bucket": "capstone-bangkit-b0a59.appspot.com"
  },
  "client": [
    {
      "client_info": {
        "mobilesdk_app_id": "1:404388630261:android:5790a20659c22b5e96ffbc",
        "android_client_info": {
          "package_name": "com.capstonebangkit.itscoffe"
        }
      },
      "oauth_client": [
        {
          "client_id": "404388630261-qs5p8roh3b047ujr50nsqoeh5us1qfgt.apps.googleusercontent.com",
          "client_type": 3
        }
      ],
      "api_key": [
        {
          "current_key": "AIzaSyDs7M26BOkYoQda6pLg-HeCUITXnF0IoDA"
        }
      ],
      "services": {
        "appinvite_service": {
          "other_platform_oauth_client": [
            {
              "client_id": "404388630261-qs5p8roh3b047ujr50nsqoeh5us1qfgt.apps.googleusercontent.com",
              "client_type": 3
            }
          ]
        }
      }
    }
  ],
  "configuration_version": "1"
}